LICENSE
MANIFEST.in
README.rst
pavement.py
setup.py
techminer/-extract_abstract_words.py
techminer/-extract_title_words.py
techminer/__init__.py
techminer/app.py
techminer.egg-info/PKG-INFO
techminer.egg-info/SOURCES.txt
techminer.egg-info/dependency_links.txt
techminer.egg-info/requires.txt
techminer.egg-info/top_level.txt
techminer/core/__init__.py
techminer/core/add_counters_to_axis.py
techminer/core/apply_institutions_thesaurus.py
techminer/core/apply_keywords_thesaurus.py
techminer/core/ca.py
techminer/core/cluster_table_to_list.py
techminer/core/cluster_table_to_python_code.py
techminer/core/clustering.py
techminer/core/corpus_filter.py
techminer/core/create_institutions_thesaurus.py
techminer/core/create_keywords_thesaurus.py
techminer/core/dashboard.py
techminer/core/dataframe.py
techminer/core/exclude_terms.py
techminer/core/explode.py
techminer/core/extract_country_name.py
techminer/core/extract_words.py
techminer/core/filter_records.py
techminer/core/keywords.py
techminer/core/keywords_coverage.py
techminer/core/logging_info.py
techminer/core/main_path.py
techminer/core/map.py
techminer/core/network.py
techminer/core/normalize_network.py
techminer/core/params.py
techminer/core/record_to_html.py
techminer/core/sort_axis.py
techminer/core/sort_by_axis.py
techminer/core/text.py
techminer/core/tf_matrix.py
techminer/core/tfidf_matrix.py
techminer/core/thesaurus.py
techminer/data/bg2am.data
techminer/data/country_codes.data
techminer/data/institutions.data
techminer/data/phrases.data
techminer/data/stopwords.data
techminer/data/worldmap.data
techminer/gui/__init__.py
techminer/gui/apply_thesaurus.py
techminer/gui/associaation_analysis.py
techminer/gui/bigraph_analysis.py
techminer/gui/bradford_law.py
techminer/gui/by_term_per_term_per_year.py
techminer/gui/citation_analysis.py
techminer/gui/co_word_analysis.py
techminer/gui/collaboration_analysis.py
techminer/gui/column_explorer.py
techminer/gui/comparative_analysis.py
techminer/gui/concept_mapping.py
techminer/gui/conceptual_structure.py
techminer/gui/core_authors_analysis.py
techminer/gui/core_sources_analysis.py
techminer/gui/correlation_analysis.py
